tiny_recursive_model/__init__.py
tiny_recursive_model/mlp_mixer_1d.py
tiny_recursive_model/trainer.py
tiny_recursive_model/trm.py
tiny_recursive_model-0.0.12.dist-info/METADATA
tiny_recursive_model-0.0.12.dist-info/WHEEL
tiny_recursive_model-0.0.12.dist-info/licenses/LICENSE
tiny_recursive_model-0.0.12.dist-info/RECORD
