Metadata-Version: 2.4
Name: tiny-recursive-model
Version: 0.0.12
Summary: Tiny Recursive Model
Project-URL: Homepage, https://pypi.org/project/tiny-recursive-model/
Project-URL: Repository, https://github.com/lucidrains/tiny-recursive-model
Author-email: Phil Wang <lucidrains@gmail.com>
License: MIT License
License-File: LICENSE
Keywords: artificial intelligence,deep learning,reasoning
Classifier: Development Status :: 4 - Beta
Classifier: Intended Audience :: Developers
Classifier: License :: OSI Approved :: MIT License
Classifier: Programming Language :: Python :: 3.9
Classifier: Topic :: Scientific/Engineering :: Artificial Intelligence
Requires-Python: >=3.9
Requires-Dist: accelerate
Requires-Dist: adam-atan2-pytorch>=0.2.2
Requires-Dist: einops>=0.8.1
Requires-Dist: ema-pytorch
Requires-Dist: torch>=2.4
Requires-Dist: x-transformers>=2.9.0
Provides-Extra: examples
Provides-Extra: test
Requires-Dist: pytest; extra == 'test'
